ros_rosgraph_msgs-2.3.0.data/data/include/rosgraph_msgs/rosgraph_msgs/msg/clock.h
ros_rosgraph_msgs-2.3.0.data/data/include/rosgraph_msgs/rosgraph_msgs/msg/clock.hpp
ros_rosgraph_msgs-2.3.0.data/data/include/rosgraph_msgs/rosgraph_msgs/msg/rosidl_generator_c__visibility_control.h
ros_rosgraph_msgs-2.3.0.data/data/include/rosgraph_msgs/rosgraph_msgs/msg/rosidl_generator_cpp__visibility_control.hpp
ros_rosgraph_msgs-2.3.0.data/data/include/rosgraph_msgs/rosgraph_msgs/msg/rosidl_typesupport_fastrtps_c__visibility_control.h
ros_rosgraph_msgs-2.3.0.data/data/include/rosgraph_msgs/rosgraph_msgs/msg/rosidl_typesupport_fastrtps_cpp__visibility_control.h
ros_rosgraph_msgs-2.3.0.data/data/include/rosgraph_msgs/rosgraph_msgs/msg/rosidl_typesupport_introspection_c__visibility_control.h
ros_rosgraph_msgs-2.3.0.data/data/include/rosgraph_msgs/rosgraph_msgs/msg/detail/clock__builder.hpp
ros_rosgraph_msgs-2.3.0.data/data/include/rosgraph_msgs/rosgraph_msgs/msg/detail/clock__description.c
ros_rosgraph_msgs-2.3.0.data/data/include/rosgraph_msgs/rosgraph_msgs/msg/detail/clock__functions.c
ros_rosgraph_msgs-2.3.0.data/data/include/rosgraph_msgs/rosgraph_msgs/msg/detail/clock__functions.h
ros_rosgraph_msgs-2.3.0.data/data/include/rosgraph_msgs/rosgraph_msgs/msg/detail/clock__rosidl_typesupport_fastrtps_c.h
ros_rosgraph_msgs-2.3.0.data/data/include/rosgraph_msgs/rosgraph_msgs/msg/detail/clock__rosidl_typesupport_fastrtps_cpp.hpp
ros_rosgraph_msgs-2.3.0.data/data/include/rosgraph_msgs/rosgraph_msgs/msg/detail/clock__rosidl_typesupport_introspection_c.h
ros_rosgraph_msgs-2.3.0.data/data/include/rosgraph_msgs/rosgraph_msgs/msg/detail/clock__rosidl_typesupport_introspection_cpp.hpp
ros_rosgraph_msgs-2.3.0.data/data/include/rosgraph_msgs/rosgraph_msgs/msg/detail/clock__struct.h
ros_rosgraph_msgs-2.3.0.data/data/include/rosgraph_msgs/rosgraph_msgs/msg/detail/clock__struct.hpp
ros_rosgraph_msgs-2.3.0.data/data/include/rosgraph_msgs/rosgraph_msgs/msg/detail/clock__traits.hpp
ros_rosgraph_msgs-2.3.0.data/data/lib/python3.13/site-packages/rosgraph_msgs-2.3.0-py3.13.egg-info/PKG-INFO
ros_rosgraph_msgs-2.3.0.data/data/lib/python3.13/site-packages/rosgraph_msgs-2.3.0-py3.13.egg-info/SOURCES.txt
ros_rosgraph_msgs-2.3.0.data/data/lib/python3.13/site-packages/rosgraph_msgs-2.3.0-py3.13.egg-info/dependency_links.txt
ros_rosgraph_msgs-2.3.0.data/data/lib/python3.13/site-packages/rosgraph_msgs-2.3.0-py3.13.egg-info/top_level.txt
ros_rosgraph_msgs-2.3.0.dist-info/METADATA
ros_rosgraph_msgs-2.3.0.dist-info/WHEEL
ros_rosgraph_msgs-2.3.0.dist-info/top_level.txt
ros_rosgraph_msgs-2.3.0.dist-info/RECORD
