Metadata-Version: 2.4
Name: ros-rosgraph-msgs
Version: 2.3.0
Summary: Provides low-level ROS message definitions for the ROS Computation Graph, such as the Clock message for time synchronization.
Requires-Dist: ros-rosidl-default-runtime~=1.7.1
Requires-Dist: ros-builtin-interfaces~=2.3.0
Dynamic: description
Dynamic: description-content-type
Dynamic: requires-dist
Dynamic: summary
